nonebot/__init__.py
nonebot/argparse.py
nonebot/default_config.py
nonebot/exceptions.py
nonebot/helpers.py
nonebot/log.py
nonebot/message.py
nonebot/natural_language.py
nonebot/notice_request.py
nonebot/permission.py
nonebot/plugin.py
nonebot/sched.py
nonebot/session.py
nonebot/typing.py
nonebot/command/__init__.py
nonebot/command/group.py
nonebot/command/group.pyi
nonebot/command/argfilter/__init__.py
nonebot/command/argfilter/controllers.py
nonebot/command/argfilter/converters.py
nonebot/command/argfilter/extractors.py
nonebot/command/argfilter/validators.py
nonebot/plugins/__init__.py
nonebot/plugins/base.py
nonebot_sanic-1.4.2.dist-info/LICENSE
nonebot_sanic-1.4.2.dist-info/METADATA
nonebot_sanic-1.4.2.dist-info/WHEEL
nonebot_sanic-1.4.2.dist-info/top_level.txt
nonebot_sanic-1.4.2.dist-info/RECORD
