Metadata-Version: 2.1
Name: nonebot-sanic
Version: 1.4.2
Summary: An asynchronous QQ bot framework based on CoolQ.
Home-page: https://github.com/richardchien/nonebot
Author: Richard Chien
Author-email: richardchienthebest@gmail.com
License: MIT License
Platform: any
Classifier: Development Status :: 5 - Production/Stable
Classifier: Framework :: Robot Framework
Classifier: Framework :: Robot Framework :: Library
Classifier: License :: OSI Approved :: MIT License
Classifier: Operating System :: OS Independent
Classifier: Programming Language :: Python :: 3
Requires-Python: >=3.7
Requires-Dist: aiocqhttp-sanic (<1.3,>=1.2)
Requires-Dist: aiocache (<1.0,>=0.10)
Provides-Extra: scheduler
Requires-Dist: apscheduler ; extra == 'scheduler'
